suplalite/__init__.py
suplalite/encoding.py
suplalite/logging.py
suplalite/network.py
suplalite/packets.py
suplalite/proto.py
suplalite/utils.py
suplalite/device/__init__.py
suplalite/device/channels.py
suplalite/server/__init__.py
suplalite/server/api.py
suplalite/server/context.py
suplalite/server/events.py
suplalite/server/handlers.py
suplalite/server/state.py
suplalite-1.1.1.dist-info/METADATA
suplalite-1.1.1.dist-info/WHEEL
suplalite-1.1.1.dist-info/licenses/LICENSE
suplalite-1.1.1.dist-info/RECORD
