Metadata-Version: 2.4
Name: suplalite
Version: 1.1.1
Summary: A lightweight implementation of SUPLA server and devices
License-Expression: GPL-3.0-or-later
License-File: LICENSE
Classifier: Operating System :: OS Independent
Classifier: Programming Language :: Python :: 3
Requires-Python: >=3.10
Requires-Dist: fastapi
Requires-Dist: tlslite-ng
Requires-Dist: uvicorn
Provides-Extra: dev
Requires-Dist: aiohttp; extra == 'dev'
Requires-Dist: build; extra == 'dev'
Requires-Dist: mypy; extra == 'dev'
Requires-Dist: pre-commit; extra == 'dev'
Requires-Dist: pylint; extra == 'dev'
Requires-Dist: pylint-pytest; extra == 'dev'
Requires-Dist: pytest; extra == 'dev'
Requires-Dist: pytest-asyncio; extra == 'dev'
Requires-Dist: pytest-cov; extra == 'dev'
Requires-Dist: pytest-xdist; extra == 'dev'
